equirc/__init__.py
equirc/keras_example.py
equirc/keras_rclayers.py
equirc/pytorch_example.py
equirc/pytorch_rclayers.py
equirc-1.0.0.dist-info/METADATA
equirc-1.0.0.dist-info/WHEEL
equirc-1.0.0.dist-info/top_level.txt
equirc-1.0.0.dist-info/RECORD
