Metadata-Version: 2.1
Name: equirc
Version: 1.0.0
Summary: Reverse Complement Equivariant Layers
Home-page: https://github.com/Vincentx15/Equi-RC
Author: Vincent Mallet, Jean-Philippe Vert
Author-email: vincent.mallet96@gmail.com
License: UNKNOWN
Platform: UNKNOWN
Classifier: Programming Language :: Python :: 3
Classifier: License :: OSI Approved :: MIT License
Classifier: Operating System :: OS Independent
